swollen/__init__.py
swollen/my_module.py
swollen-0.0.1.dist-info/LICENSE
swollen-0.0.1.dist-info/METADATA
swollen-0.0.1.dist-info/WHEEL
swollen-0.0.1.dist-info/top_level.txt
swollen-0.0.1.dist-info/RECORD
