Metadata-Version: 2.1
Name: swollen
Version: 0.0.1
Summary: A brief description of your package
Home-page: https://github.com/ftymoshchuk
Author: FedirT
Author-email: ftymoshchuk@gmail.com
Classifier: Programming Language :: Python :: 3
Classifier: License :: OSI Approved :: MIT License
Classifier: Operating System :: OS Independent
Requires-Python: >=3.6
License-File: LICENSE
